<?xml version="1.0" encoding="utf-8"?>
<Defs>
    <ThingDef Name="MMDrugBase" ParentName="DrugBase" Abstract="True">
      <ingestible>
        <drugCategory>Medical</drugCategory>
        <chairSearchRadius>0</chairSearchRadius>
        <ingestHoldUsesTable>false</ingestHoldUsesTable>
        <maxNumToIngestAtOnce>1</maxNumToIngestAtOnce>
        <preferability>NeverForNutrition</preferability>
        <ingestHoldOffsetStanding>
        <northDefault>
          <offset>(0.18,0,0)</offset>
        </northDefault>
      </ingestHoldOffsetStanding>
    </ingestible>
    <socialPropernessMatters>true</socialPropernessMatters>
    <thingCategories Inherit="false">
      <li>AYDrugs</li>
    </thingCategories>
  </ThingDef>
  
   <ThingDef Name="MMDrugOintmentBase" ParentName="MMDrugBase" Abstract="True">
    <ingestible>
      <foodType>Processed, Fluid</foodType>
      <baseIngestTicks>100</baseIngestTicks>
      <ingestSound>RawMeat_Eat</ingestSound>
      <ingestCommandString>Apply {0}</ingestCommandString>
      <ingestReportString>Applying {0}.</ingestReportString>
    </ingestible>
    <thingCategories Inherit="false">
      <li>AYOintments</li>
    </thingCategories>
  </ThingDef>
  
  <ThingDef ParentName="MMDrugOintmentBase">
    <defName>MMScarCream</defName>
    <label>Scar Cream</label>
    <description>Scar cream is an antibiotic and regenerative skin cream designed to help with permanent scar injuries. It is capable of healing permanent scars. Healing effects last 1.0 days.</description>
    <graphicData>
      <texPath>Things/Item/Drug/MMScarCream</texPath>
      <graphicClass>Graphic_Single</graphicClass>
    </graphicData>
    <socialPropernessMatters>false</socialPropernessMatters>
    <rotatable>false</rotatable>
    <statBases>
      <WorkToMake>300</WorkToMake>
      <MarketValue>52</MarketValue>
      <!-- MH: 30, T: 5 x 0.5, AO: 2 x 7, YO: 1 x 5.5 -->
      <Mass>0.2</Mass>
    </statBases>
    <techLevel>Medieval</techLevel>
    <ingestible>
      <outcomeDoers>
        <li Class="IngestionOutcomeDoer_GiveHediff">
          <hediffDef>MMScarCreamHigh</hediffDef>
          <severity>1.0</severity>
        </li>
      </outcomeDoers>
    </ingestible>
    <comps>
      <li Class="CompProperties_Drug">
        <listOrder>3588</listOrder>
        <overdoseSeverityOffset>
          <min>0.01</min>
          <max>0.03</max>
        </overdoseSeverityOffset>
      </li>
    </comps>
  </ThingDef>
